extract_vcf/__init__.py
extract_vcf/config_parser.py
extract_vcf/get_annotations.py
extract_vcf/log.py
extract_vcf/plugin.py
extract_vcf-0.5.dist-info/DESCRIPTION.rst
extract_vcf-0.5.dist-info/METADATA
extract_vcf-0.5.dist-info/RECORD
extract_vcf-0.5.dist-info/WHEEL
extract_vcf-0.5.dist-info/metadata.json
extract_vcf-0.5.dist-info/top_level.txt
