Metadata-Version: 2.0
Name: extract-vcf
Version: 0.5
Summary: Tool to extract information from vcf file.
Home-page: https://github.com/moonso/extract_vcf
Author: Måns Magnusson
Author-email: mans.magnusson@scilifelab.se
License: MIT License
Platform: UNKNOWN
Classifier: Intended Audience :: Developers
Classifier: License :: OSI Approved :: BSD License
Classifier: Operating System :: OS Independent
Classifier: Programming Language :: Python
Classifier: Topic :: Software Development :: Libraries
Requires-Dist: configobj
